qtimgren/__init__.py
qtimgren/__main__.py
qtimgren/about.py
qtimgren/abstract_view.py
qtimgren/app.py
qtimgren/main_view.py
qtimgren/main_window.py
qtimgren/merge.py
qtimgren/merge_dialog.py
qtimgren/profile.py
qtimgren/profile_manager.py
qtimgren/profiles.py
qtimgren/qtimgren_fr.ts
qtimgren/rc_qtimgren.py
qtimgren/settings.py
qtimgren/sql_cache.py
qtimgren/ui_about.py
qtimgren/ui_main_window.py
qtimgren/ui_merge.py
qtimgren/ui_profile.py
qtimgren/ui_profiles.py
qtimgren/ui_settings.py
qtimgren/version.py
qtimgren-0.5.2.dist-info/METADATA
qtimgren-0.5.2.dist-info/WHEEL
qtimgren-0.5.2.dist-info/licenses/LICENCE.txt
qtimgren-0.5.2.dist-info/RECORD
