Metadata-Version: 2.4
Name: qtimgren
Version: 0.5.2
Summary: GUI over the pyimgren package
Project-URL: Changelog, https://github.com/s-ball/qtimgren/blob/master/CHANGES.txt
Project-URL: Issues, https://github.com/s-ball/qtimgren/issues
Project-URL: Source, https://github.com/s-ball/qtimgren
Author-email: s-ball <s-ball@laposte.net>
License-Expression: MIT
License-File: LICENCE.txt
Classifier: Development Status :: 2 - Pre-Alpha
Classifier: Environment :: X11 Applications :: Qt
Classifier: Intended Audience :: End Users/Desktop
Classifier: License :: OSI Approved :: MIT License
Classifier: Operating System :: OS Independent
Classifier: Programming Language :: Python
Classifier: Programming Language :: Python :: 3.9
Classifier: Programming Language :: Python :: 3.10
Classifier: Programming Language :: Python :: 3.11
Classifier: Programming Language :: Python :: 3.12
Classifier: Programming Language :: Python :: 3.13
Classifier: Programming Language :: Python :: Implementation :: CPython
Classifier: Topic :: Multimedia :: Graphics
Requires-Python: >=3.9
Requires-Dist: pyimgren>=1.0
Requires-Dist: pyside6
Provides-Extra: cfg
Requires-Dist: hatch-pyside; extra == 'cfg'
